README.md
setup.py
qad_api/__init__.py
qad_api/__version__.py
qad_api.egg-info/PKG-INFO
qad_api.egg-info/SOURCES.txt
qad_api.egg-info/dependency_links.txt
qad_api.egg-info/requires.txt
qad_api.egg-info/top_level.txt
qad_api/account/__init__.py
qad_api/account/account_api.py
qad_api/core/__init__.py
qad_api/core/exceptions.py
qad_api/core/qad_api.py
qad_api/core/session.py
qad_api/core/internal/__init__.py
qad_api/core/internal/backend.py
qad_api/core/internal/module.py
qad_api/core/internal/models/__init__.py
qad_api/core/internal/models/job_base.py
qad_api/core/internal/models/named_object.py
qad_api/core/internal/models/object.py
qad_api/core/internal/models/pagination.py
qad_api/core/internal/util/__init__.py
qad_api/core/internal/util/serialization.py
qad_api/lattice/__init__.py
qad_api/lattice/lattice_api.py
qad_api/lattice/systems.py
qad_api/lattice/unit_cells.py
qad_api/lattice/models/__init__.py
qad_api/lattice/models/system.py
qad_api/lattice/models/unit_cell.py
qad_api/lattice/scce/__init__.py
qad_api/lattice/scce/jobs.py
qad_api/lattice/scce/scce.py
qad_api/lattice/scce/models/__init__.py
qad_api/lattice/scce/models/job.py