Metadata-Version: 2.1
Name: qad-api
Version: 0.1.dev0
Summary: UNKNOWN
Home-page: https://github.com/HQSquantumsimulations/qad-api/
Author: Sebastian Lehmann
Author-email: sebastian.lehmann@quantumsimulations.de
License: Apache License, Version 2.0
Platform: UNKNOWN
